LICENSE
MANIFEST.in
README.rst
setup.py
djangonetsol_polls.egg-info/PKG-INFO
djangonetsol_polls.egg-info/SOURCES.txt
djangonetsol_polls.egg-info/dependency_links.txt
djangonetsol_polls.egg-info/top_level.txt
polls/__init__.py
polls/admin.py
polls/models.py
polls/tests.py
polls/urls.py
polls/views.py
polls/templates/polls/details.html
polls/templates/polls/index.html
polls/templates/polls/results.html