Metadata-Version: 1.1
Name: djangonetsol-polls
Version: 0.1
Summary: A simple Django app to conduct Web-based polls.
Home-page: http://netsolutions.com/
Author: Netsolutions
Author-email: anshu.sharma@netsolutions.in
License: BSD License
Platform: UNKNOWN
Classifier: Environment :: Web Environment
Classifier: Framework :: Django
Classifier: Intended Audience :: Developers
Classifier: License :: OSI Approved :: BSD License
Classifier: Operating System :: OS Independent
Classifier: Programming Language :: Python
Classifier: Programming Language :: Python :: 3
Classifier: Programming Language :: Python :: 3.2
Classifier: Programming Language :: Python :: 3.3
Classifier: Topic :: Internet :: WWW/HTTP
Classifier: Topic :: Internet :: WWW/HTTP :: Dynamic Content
